[{"projectId":"prj_TEhZ3iXh2MfgelKntnyiJGpEFO9P","TimeUTC":"2025-12-12 14:20:07","timestampInMs":1765549207044,"requestPath":"api.gaiyatime.com/api/quota-status","requestMethod":"GET","requestQueryString":"user_id=f76fae0e-1e5b-40f1-9c8d-0d138aa65639&user_tier=pro","responseStatusCode":200,"requestId":"247g4-1765549207003-3797c7fd1965","requestUserAgent":"python-requests/2.32.4","environment":"production","branch":"main","vercelCache":"MISS","host":"api.gaiyatime.com","deploymentDomain":"api.gaiyatime.com","deploymentId":"dpl_2aMNxyLN1UYnCCzhMVrg1pooffv1","traceId":"","sessionId":"","type":"serverless","function":"/api/quota-status","level":"error","message":"Quota status function called","durationMs":"","region":"","maxMemoryUsed":"","memorySize":"","invocationId":"","instanceId":"","concurrency":""},{"projectId":"prj_TEhZ3iXh2MfgelKntnyiJGpEFO9P","TimeUTC":"2025-12-12 14:20:07","timestampInMs":1765549207044,"requestPath":"api.gaiyatime.com/api/quota-status","requestMethod":"GET","requestQueryString":"user_id=f76fae0e-1e5b-40f1-9c8d-0d138aa65639&user_tier=pro","responseStatusCode":200,"requestId":"247g4-1765549207003-3797c7fd1965","requestUserAgent":"python-requests/2.32.4","environment":"production","branch":"main","vercelCache":"MISS","host":"api.gaiyatime.com","deploymentDomain":"api.gaiyatime.com","deploymentId":"dpl_2aMNxyLN1UYnCCzhMVrg1pooffv1","traceId":"","sessionId":"","type":"serverless","function":"/api/quota-status","level":"error","message":"User: f76fae0e-1e5b-40f1-9c8d-0d138aa65639, Tier: pro","durationMs":"","region":"","maxMemoryUsed":"","memorySize":"","invocationId":"","instanceId":"","concurrency":""},{"projectId":"prj_TEhZ3iXh2MfgelKntnyiJGpEFO9P","TimeUTC":"2025-12-12 14:20:07","timestampInMs":1765549207055,"requestPath":"api.gaiyatime.com/api/quota-status","requestMethod":"GET","requestQueryString":"user_id=f76fae0e-1e5b-40f1-9c8d-0d138aa65639&user_tier=pro","responseStatusCode":200,"requestId":"247g4-1765549207003-3797c7fd1965","requestUserAgent":"python-requests/2.32.4","environment":"production","branch":"main","vercelCache":"MISS","host":"api.gaiyatime.com","deploymentDomain":"api.gaiyatime.com","deploymentId":"dpl_2aMNxyLN1UYnCCzhMVrg1pooffv1","traceId":"","sessionId":"","type":"serverless","function":"/api/quota-status","level":"error","message":"Supabase client initialized successfully","durationMs":"","region":"","maxMemoryUsed":"","memorySize":"","invocationId":"","instanceId":"","concurrency":""},{"projectId":"prj_TEhZ3iXh2MfgelKntnyiJGpEFO9P","TimeUTC":"2025-12-12 14:20:07","timestampInMs":1765549207911,"requestPath":"api.gaiyatime.com/api/quota-status","requestMethod":"GET","requestQueryString":"user_id=f76fae0e-1e5b-40f1-9c8d-0d138aa65639&user_tier=pro","responseStatusCode":200,"requestId":"247g4-1765549207003-3797c7fd1965","requestUserAgent":"python-requests/2.32.4","environment":"production","branch":"main","vercelCache":"MISS","host":"api.gaiyatime.com","deploymentDomain":"api.gaiyatime.com","deploymentId":"dpl_2aMNxyLN1UYnCCzhMVrg1pooffv1","traceId":"","sessionId":"","type":"serverless","function":"/api/quota-status","level":"info","message":"HTTP Request: GET https://qpgypaxwjgcirssydgqh.supabase.co/rest/v1/user_quotas?select=%2A&user_id=eq.f76fae0e-1e5b-40f1-9c8d-0d138aa65639 \"HTTP/2 200 OK\"","durationMs":"","region":"","maxMemoryUsed":"","memorySize":"","invocationId":"","instanceId":"","concurrency":""},{"projectId":"prj_TEhZ3iXh2MfgelKntnyiJGpEFO9P","TimeUTC":"2025-12-12 14:20:07","timestampInMs":1765549207911,"requestPath":"api.gaiyatime.com/api/quota-status","requestMethod":"GET","requestQueryString":"user_id=f76fae0e-1e5b-40f1-9c8d-0d138aa65639&user_tier=pro","responseStatusCode":200,"requestId":"247g4-1765549207003-3797c7fd1965","requestUserAgent":"python-requests/2.32.4","environment":"production","branch":"main","vercelCache":"MISS","host":"api.gaiyatime.com","deploymentDomain":"api.gaiyatime.com","deploymentId":"dpl_2aMNxyLN1UYnCCzhMVrg1pooffv1","traceId":"","sessionId":"","type":"serverless","function":"/api/quota-status","level":"error","message":"Returning quota: {'remaining': {'daily_plan': 17, 'weekly_report': 10, 'chat': 100}, 'user_tier': 'pro'}","durationMs":"","region":"","maxMemoryUsed":"","memorySize":"","invocationId":"","instanceId":"","concurrency":""},{"projectId":"prj_TEhZ3iXh2MfgelKntnyiJGpEFO9P","TimeUTC":"2025-12-12 14:20:07","timestampInMs":1765549207911,"requestPath":"api.gaiyatime.com/api/quota-status","requestMethod":"GET","requestQueryString":"user_id=f76fae0e-1e5b-40f1-9c8d-0d138aa65639&user_tier=pro","responseStatusCode":200,"requestId":"247g4-1765549207003-3797c7fd1965","requestUserAgent":"python-requests/2.32.4","environment":"production","branch":"main","vercelCache":"MISS","host":"api.gaiyatime.com","deploymentDomain":"api.gaiyatime.com","deploymentId":"dpl_2aMNxyLN1UYnCCzhMVrg1pooffv1","traceId":"","sessionId":"","type":"serverless","function":"/api/quota-status","level":"info","message":"127.0.0.1 - - [12/Dec/2025 14:20:07] \"GET /api/quota-status?user_id=f76fae0e-1e5b-40f1-9c8d-0d138aa65639&user_tier=pro HTTP/1.1\" 200 -","durationMs":"","region":"","maxMemoryUsed":"","memorySize":"","invocationId":"","instanceId":"","concurrency":""},{"projectId":"prj_TEhZ3iXh2MfgelKntnyiJGpEFO9P","TimeUTC":"2025-12-12 14:20:07","timestampInMs":1765549207003,"requestPath":"api.gaiyatime.com/api/quota-status","requestMethod":"GET","requestQueryString":"user_id=f76fae0e-1e5b-40f1-9c8d-0d138aa65639&user_tier=pro","responseStatusCode":200,"requestId":"247g4-1765549207003-3797c7fd1965","requestUserAgent":"python-requests/2.32.4","environment":"production","branch":"main","vercelCache":"MISS","host":"api.gaiyatime.com","deploymentDomain":"api.gaiyatime.com","deploymentId":"dpl_2aMNxyLN1UYnCCzhMVrg1pooffv1","traceId":"","sessionId":"","type":"serverless","function":"/api/quota-status","level":"","message":"","durationMs":868,"region":"iad1","maxMemoryUsed":275,"memorySize":2048,"invocationId":"01KC9EXTJ10TQE6RKANC70N344","instanceId":"SolRvrylshif","concurrency":4},{"projectId":"prj_TEhZ3iXh2MfgelKntnyiJGpEFO9P","TimeUTC":"2025-12-12 14:20:06","timestampInMs":1765549206753,"requestPath":"api.gaiyatime.com/api/quota-status","requestMethod":"GET","requestQueryString":"user_id=f76fae0e-1e5b-40f1-9c8d-0d138aa65639&user_tier=pro","responseStatusCode":200,"requestId":"mwfz6-1765549206705-ce760e30c39f","requestUserAgent":"python-requests/2.32.4","environment":"production","branch":"main","vercelCache":"MISS","host":"api.gaiyatime.com","deploymentDomain":"api.gaiyatime.com","deploymentId":"dpl_2aMNxyLN1UYnCCzhMVrg1pooffv1","traceId":"","sessionId":"","type":"serverless","function":"/api/quota-status","level":"error","message":"Quota status function called","durationMs":"","region":"","maxMemoryUsed":"","memorySize":"","invocationId":"","instanceId":"","concurrency":""},{"projectId":"prj_TEhZ3iXh2MfgelKntnyiJGpEFO9P","TimeUTC":"2025-12-12 14:20:06","timestampInMs":1765549206753,"requestPath":"api.gaiyatime.com/api/quota-status","requestMethod":"GET","requestQueryString":"user_id=f76fae0e-1e5b-40f1-9c8d-0d138aa65639&user_tier=pro","responseStatusCode":200,"requestId":"mwfz6-1765549206705-ce760e30c39f","requestUserAgent":"python-requests/2.32.4","environment":"production","branch":"main","vercelCache":"MISS","host":"api.gaiyatime.com","deploymentDomain":"api.gaiyatime.com","deploymentId":"dpl_2aMNxyLN1UYnCCzhMVrg1pooffv1","traceId":"","sessionId":"","type":"serverless","function":"/api/quota-status","level":"error","message":"User: f76fae0e-1e5b-40f1-9c8d-0d138aa65639, Tier: pro","durationMs":"","region":"","maxMemoryUsed":"","memorySize":"","invocationId":"","instanceId":"","concurrency":""},{"projectId":"prj_TEhZ3iXh2MfgelKntnyiJGpEFO9P","TimeUTC":"2025-12-12 14:20:06","timestampInMs":1765549206764,"requestPath":"api.gaiyatime.com/api/quota-status","requestMethod":"GET","requestQueryString":"user_id=f76fae0e-1e5b-40f1-9c8d-0d138aa65639&user_tier=pro","responseStatusCode":200,"requestId":"mwfz6-1765549206705-ce760e30c39f","requestUserAgent":"python-requests/2.32.4","environment":"production","branch":"main","vercelCache":"MISS","host":"api.gaiyatime.com","deploymentDomain":"api.gaiyatime.com","deploymentId":"dpl_2aMNxyLN1UYnCCzhMVrg1pooffv1","traceId":"","sessionId":"","type":"serverless","function":"/api/quota-status","level":"error","message":"Supabase client initialized successfully","durationMs":"","region":"","maxMemoryUsed":"","memorySize":"","invocationId":"","instanceId":"","concurrency":""},{"projectId":"prj_TEhZ3iXh2MfgelKntnyiJGpEFO9P","TimeUTC":"2025-12-12 14:20:07","timestampInMs":1765549207591,"requestPath":"api.gaiyatime.com/api/quota-status","requestMethod":"GET","requestQueryString":"user_id=f76fae0e-1e5b-40f1-9c8d-0d138aa65639&user_tier=pro","responseStatusCode":200,"requestId":"mwfz6-1765549206705-ce760e30c39f","requestUserAgent":"python-requests/2.32.4","environment":"production","branch":"main","vercelCache":"MISS","host":"api.gaiyatime.com","deploymentDomain":"api.gaiyatime.com","deploymentId":"dpl_2aMNxyLN1UYnCCzhMVrg1pooffv1","traceId":"","sessionId":"","type":"serverless","function":"/api/quota-status","level":"info","message":"HTTP Request: GET https://qpgypaxwjgcirssydgqh.supabase.co/rest/v1/user_quotas?select=%2A&user_id=eq.f76fae0e-1e5b-40f1-9c8d-0d138aa65639 \"HTTP/2 200 OK\"","durationMs":"","region":"","maxMemoryUsed":"","memorySize":"","invocationId":"","instanceId":"","concurrency":""},{"projectId":"prj_TEhZ3iXh2MfgelKntnyiJGpEFO9P","TimeUTC":"2025-12-12 14:20:07","timestampInMs":1765549207592,"requestPath":"api.gaiyatime.com/api/quota-status","requestMethod":"GET","requestQueryString":"user_id=f76fae0e-1e5b-40f1-9c8d-0d138aa65639&user_tier=pro","responseStatusCode":200,"requestId":"mwfz6-1765549206705-ce760e30c39f","requestUserAgent":"python-requests/2.32.4","environment":"production","branch":"main","vercelCache":"MISS","host":"api.gaiyatime.com","deploymentDomain":"api.gaiyatime.com","deploymentId":"dpl_2aMNxyLN1UYnCCzhMVrg1pooffv1","traceId":"","sessionId":"","type":"serverless","function":"/api/quota-status","level":"error","message":"User tier changed: free -> pro, updating...","durationMs":"","region":"","maxMemoryUsed":"","memorySize":"","invocationId":"","instanceId":"","concurrency":""},{"projectId":"prj_TEhZ3iXh2MfgelKntnyiJGpEFO9P","TimeUTC":"2025-12-12 14:20:08","timestampInMs":1765549208396,"requestPath":"api.gaiyatime.com/api/quota-status","requestMethod":"GET","requestQueryString":"user_id=f76fae0e-1e5b-40f1-9c8d-0d138aa65639&user_tier=pro","responseStatusCode":200,"requestId":"mwfz6-1765549206705-ce760e30c39f","requestUserAgent":"python-requests/2.32.4","environment":"production","branch":"main","vercelCache":"MISS","host":"api.gaiyatime.com","deploymentDomain":"api.gaiyatime.com","deploymentId":"dpl_2aMNxyLN1UYnCCzhMVrg1pooffv1","traceId":"","sessionId":"","type":"serverless","function":"/api/quota-status","level":"info","message":"HTTP Request: PATCH https://qpgypaxwjgcirssydgqh.supabase.co/rest/v1/user_quotas?user_id=eq.f76fae0e-1e5b-40f1-9c8d-0d138aa65639 \"HTTP/2 200 OK\"","durationMs":"","region":"","maxMemoryUsed":"","memorySize":"","invocationId":"","instanceId":"","concurrency":""},{"projectId":"prj_TEhZ3iXh2MfgelKntnyiJGpEFO9P","TimeUTC":"2025-12-12 14:20:08","timestampInMs":1765549208397,"requestPath":"api.gaiyatime.com/api/quota-status","requestMethod":"GET","requestQueryString":"user_id=f76fae0e-1e5b-40f1-9c8d-0d138aa65639&user_tier=pro","responseStatusCode":200,"requestId":"mwfz6-1765549206705-ce760e30c39f","requestUserAgent":"python-requests/2.32.4","environment":"production","branch":"main","vercelCache":"MISS","host":"api.gaiyatime.com","deploymentDomain":"api.gaiyatime.com","deploymentId":"dpl_2aMNxyLN1UYnCCzhMVrg1pooffv1","traceId":"","sessionId":"","type":"serverless","function":"/api/quota-status","level":"error","message":"Updated user tier from free to pro","durationMs":"","region":"","maxMemoryUsed":"","memorySize":"","invocationId":"","instanceId":"","concurrency":""},{"projectId":"prj_TEhZ3iXh2MfgelKntnyiJGpEFO9P","TimeUTC":"2025-12-12 14:20:08","timestampInMs":1765549208689,"requestPath":"api.gaiyatime.com/api/quota-status","requestMethod":"GET","requestQueryString":"user_id=f76fae0e-1e5b-40f1-9c8d-0d138aa65639&user_tier=pro","responseStatusCode":200,"requestId":"mwfz6-1765549206705-ce760e30c39f","requestUserAgent":"python-requests/2.32.4","environment":"production","branch":"main","vercelCache":"MISS","host":"api.gaiyatime.com","deploymentDomain":"api.gaiyatime.com","deploymentId":"dpl_2aMNxyLN1UYnCCzhMVrg1pooffv1","traceId":"","sessionId":"","type":"serverless","function":"/api/quota-status","level":"info","message":"HTTP Request: GET https://qpgypaxwjgcirssydgqh.supabase.co/rest/v1/user_quotas?select=%2A&user_id=eq.f76fae0e-1e5b-40f1-9c8d-0d138aa65639 \"HTTP/2 200 OK\"","durationMs":"","region":"","maxMemoryUsed":"","memorySize":"","invocationId":"","instanceId":"","concurrency":""},{"projectId":"prj_TEhZ3iXh2MfgelKntnyiJGpEFO9P","TimeUTC":"2025-12-12 14:20:08","timestampInMs":1765549208690,"requestPath":"api.gaiyatime.com/api/quota-status","requestMethod":"GET","requestQueryString":"user_id=f76fae0e-1e5b-40f1-9c8d-0d138aa65639&user_tier=pro","responseStatusCode":200,"requestId":"mwfz6-1765549206705-ce760e30c39f","requestUserAgent":"python-requests/2.32.4","environment":"production","branch":"main","vercelCache":"MISS","host":"api.gaiyatime.com","deploymentDomain":"api.gaiyatime.com","deploymentId":"dpl_2aMNxyLN1UYnCCzhMVrg1pooffv1","traceId":"","sessionId":"","type":"serverless","function":"/api/quota-status","level":"error","message":"Returning quota: {'remaining': {'daily_plan': 17, 'weekly_report': 10, 'chat': 100}, 'user_tier': 'pro'}","durationMs":"","region":"","maxMemoryUsed":"","memorySize":"","invocationId":"","instanceId":"","concurrency":""},{"projectId":"prj_TEhZ3iXh2MfgelKntnyiJGpEFO9P","TimeUTC":"2025-12-12 14:20:08","timestampInMs":1765549208690,"requestPath":"api.gaiyatime.com/api/quota-status","requestMethod":"GET","requestQueryString":"user_id=f76fae0e-1e5b-40f1-9c8d-0d138aa65639&user_tier=pro","responseStatusCode":200,"requestId":"mwfz6-1765549206705-ce760e30c39f","requestUserAgent":"python-requests/2.32.4","environment":"production","branch":"main","vercelCache":"MISS","host":"api.gaiyatime.com","deploymentDomain":"api.gaiyatime.com","deploymentId":"dpl_2aMNxyLN1UYnCCzhMVrg1pooffv1","traceId":"","sessionId":"","type":"serverless","function":"/api/quota-status","level":"info","message":"127.0.0.1 - - [12/Dec/2025 14:20:08] \"GET /api/quota-status?user_id=f76fae0e-1e5b-40f1-9c8d-0d138aa65639&user_tier=pro HTTP/1.1\" 200 -","durationMs":"","region":"","maxMemoryUsed":"","memorySize":"","invocationId":"","instanceId":"","concurrency":""},{"projectId":"prj_TEhZ3iXh2MfgelKntnyiJGpEFO9P","TimeUTC":"2025-12-12 14:20:06","timestampInMs":1765549206705,"requestPath":"api.gaiyatime.com/api/quota-status","requestMethod":"GET","requestQueryString":"user_id=f76fae0e-1e5b-40f1-9c8d-0d138aa65639&user_tier=pro","responseStatusCode":200,"requestId":"mwfz6-1765549206705-ce760e30c39f","requestUserAgent":"python-requests/2.32.4","environment":"production","branch":"main","vercelCache":"MISS","host":"api.gaiyatime.com","deploymentDomain":"api.gaiyatime.com","deploymentId":"dpl_2aMNxyLN1UYnCCzhMVrg1pooffv1","traceId":"","sessionId":"","type":"serverless","function":"/api/quota-status","level":"","message":"","durationMs":1937,"region":"iad1","maxMemoryUsed":275,"memorySize":2048,"invocationId":"01KC9EXTJ10TQE6RKANC70N344","instanceId":"SolRvrylshif","concurrency":4},{"projectId":"prj_TEhZ3iXh2MfgelKntnyiJGpEFO9P","TimeUTC":"2025-12-12 14:20:06","timestampInMs":1765549206417,"requestPath":"api.gaiyatime.com/api/quota-status","requestMethod":"GET","requestQueryString":"user_id=f76fae0e-1e5b-40f1-9c8d-0d138aa65639&user_tier=pro","responseStatusCode":200,"requestId":"r8wxh-1765549206367-818f6cddeb05","requestUserAgent":"python-requests/2.32.4","environment":"production","branch":"main","vercelCache":"MISS","host":"api.gaiyatime.com","deploymentDomain":"api.gaiyatime.com","deploymentId":"dpl_2aMNxyLN1UYnCCzhMVrg1pooffv1","traceId":"","sessionId":"","type":"serverless","function":"/api/quota-status","level":"error","message":"Quota status function called","durationMs":"","region":"","maxMemoryUsed":"","memorySize":"","invocationId":"","instanceId":"","concurrency":""},{"projectId":"prj_TEhZ3iXh2MfgelKntnyiJGpEFO9P","TimeUTC":"2025-12-12 14:20:06","timestampInMs":1765549206417,"requestPath":"api.gaiyatime.com/api/quota-status","requestMethod":"GET","requestQueryString":"user_id=f76fae0e-1e5b-40f1-9c8d-0d138aa65639&user_tier=pro","responseStatusCode":200,"requestId":"r8wxh-1765549206367-818f6cddeb05","requestUserAgent":"python-requests/2.32.4","environment":"production","branch":"main","vercelCache":"MISS","host":"api.gaiyatime.com","deploymentDomain":"api.gaiyatime.com","deploymentId":"dpl_2aMNxyLN1UYnCCzhMVrg1pooffv1","traceId":"","sessionId":"","type":"serverless","function":"/api/quota-status","level":"error","message":"User: f76fae0e-1e5b-40f1-9c8d-0d138aa65639, Tier: pro","durationMs":"","region":"","maxMemoryUsed":"","memorySize":"","invocationId":"","instanceId":"","concurrency":""},{"projectId":"prj_TEhZ3iXh2MfgelKntnyiJGpEFO9P","TimeUTC":"2025-12-12 14:20:06","timestampInMs":1765549206427,"requestPath":"api.gaiyatime.com/api/quota-status","requestMethod":"GET","requestQueryString":"user_id=f76fae0e-1e5b-40f1-9c8d-0d138aa65639&user_tier=pro","responseStatusCode":200,"requestId":"r8wxh-1765549206367-818f6cddeb05","requestUserAgent":"python-requests/2.32.4","environment":"production","branch":"main","vercelCache":"MISS","host":"api.gaiyatime.com","deploymentDomain":"api.gaiyatime.com","deploymentId":"dpl_2aMNxyLN1UYnCCzhMVrg1pooffv1","traceId":"","sessionId":"","type":"serverless","function":"/api/quota-status","level":"error","message":"Supabase client initialized successfully","durationMs":"","region":"","maxMemoryUsed":"","memorySize":"","invocationId":"","instanceId":"","concurrency":""},{"projectId":"prj_TEhZ3iXh2MfgelKntnyiJGpEFO9P","TimeUTC":"2025-12-12 14:20:07","timestampInMs":1765549207290,"requestPath":"api.gaiyatime.com/api/quota-status","requestMethod":"GET","requestQueryString":"user_id=f76fae0e-1e5b-40f1-9c8d-0d138aa65639&user_tier=pro","responseStatusCode":200,"requestId":"r8wxh-1765549206367-818f6cddeb05","requestUserAgent":"python-requests/2.32.4","environment":"production","branch":"main","vercelCache":"MISS","host":"api.gaiyatime.com","deploymentDomain":"api.gaiyatime.com","deploymentId":"dpl_2aMNxyLN1UYnCCzhMVrg1pooffv1","traceId":"","sessionId":"","type":"serverless","function":"/api/quota-status","level":"info","message":"HTTP Request: GET https://qpgypaxwjgcirssydgqh.supabase.co/rest/v1/user_quotas?select=%2A&user_id=eq.f76fae0e-1e5b-40f1-9c8d-0d138aa65639 \"HTTP/2 200 OK\"","durationMs":"","region":"","maxMemoryUsed":"","memorySize":"","invocationId":"","instanceId":"","concurrency":""},{"projectId":"prj_TEhZ3iXh2MfgelKntnyiJGpEFO9P","TimeUTC":"2025-12-12 14:20:07","timestampInMs":1765549207291,"requestPath":"api.gaiyatime.com/api/quota-status","requestMethod":"GET","requestQueryString":"user_id=f76fae0e-1e5b-40f1-9c8d-0d138aa65639&user_tier=pro","responseStatusCode":200,"requestId":"r8wxh-1765549206367-818f6cddeb05","requestUserAgent":"python-requests/2.32.4","environment":"production","branch":"main","vercelCache":"MISS","host":"api.gaiyatime.com","deploymentDomain":"api.gaiyatime.com","deploymentId":"dpl_2aMNxyLN1UYnCCzhMVrg1pooffv1","traceId":"","sessionId":"","type":"serverless","function":"/api/quota-status","level":"error","message":"User tier changed: free -> pro, updating...","durationMs":"","region":"","maxMemoryUsed":"","memorySize":"","invocationId":"","instanceId":"","concurrency":""},{"projectId":"prj_TEhZ3iXh2MfgelKntnyiJGpEFO9P","TimeUTC":"2025-12-12 14:20:08","timestampInMs":1765549208075,"requestPath":"api.gaiyatime.com/api/quota-status","requestMethod":"GET","requestQueryString":"user_id=f76fae0e-1e5b-40f1-9c8d-0d138aa65639&user_tier=pro","responseStatusCode":200,"requestId":"r8wxh-1765549206367-818f6cddeb05","requestUserAgent":"python-requests/2.32.4","environment":"production","branch":"main","vercelCache":"MISS","host":"api.gaiyatime.com","deploymentDomain":"api.gaiyatime.com","deploymentId":"dpl_2aMNxyLN1UYnCCzhMVrg1pooffv1","traceId":"","sessionId":"","type":"serverless","function":"/api/quota-status","level":"info","message":"HTTP Request: PATCH https://qpgypaxwjgcirssydgqh.supabase.co/rest/v1/user_quotas?user_id=eq.f76fae0e-1e5b-40f1-9c8d-0d138aa65639 \"HTTP/2 200 OK\"","durationMs":"","region":"","maxMemoryUsed":"","memorySize":"","invocationId":"","instanceId":"","concurrency":""},{"projectId":"prj_TEhZ3iXh2MfgelKntnyiJGpEFO9P","TimeUTC":"2025-12-12 14:20:08","timestampInMs":1765549208076,"requestPath":"api.gaiyatime.com/api/quota-status","requestMethod":"GET","requestQueryString":"user_id=f76fae0e-1e5b-40f1-9c8d-0d138aa65639&user_tier=pro","responseStatusCode":200,"requestId":"r8wxh-1765549206367-818f6cddeb05","requestUserAgent":"python-requests/2.32.4","environment":"production","branch":"main","vercelCache":"MISS","host":"api.gaiyatime.com","deploymentDomain":"api.gaiyatime.com","deploymentId":"dpl_2aMNxyLN1UYnCCzhMVrg1pooffv1","traceId":"","sessionId":"","type":"serverless","function":"/api/quota-status","level":"error","message":"Updated user tier from free to pro","durationMs":"","region":"","maxMemoryUsed":"","memorySize":"","invocationId":"","instanceId":"","concurrency":""},{"projectId":"prj_TEhZ3iXh2MfgelKntnyiJGpEFO9P","TimeUTC":"2025-12-12 14:20:08","timestampInMs":1765549208372,"requestPath":"api.gaiyatime.com/api/quota-status","requestMethod":"GET","requestQueryString":"user_id=f76fae0e-1e5b-40f1-9c8d-0d138aa65639&user_tier=pro","responseStatusCode":200,"requestId":"r8wxh-1765549206367-818f6cddeb05","requestUserAgent":"python-requests/2.32.4","environment":"production","branch":"main","vercelCache":"MISS","host":"api.gaiyatime.com","deploymentDomain":"api.gaiyatime.com","deploymentId":"dpl_2aMNxyLN1UYnCCzhMVrg1pooffv1","traceId":"","sessionId":"","type":"serverless","function":"/api/quota-status","level":"info","message":"HTTP Request: GET https://qpgypaxwjgcirssydgqh.supabase.co/rest/v1/user_quotas?select=%2A&user_id=eq.f76fae0e-1e5b-40f1-9c8d-0d138aa65639 \"HTTP/2 200 OK\"","durationMs":"","region":"","maxMemoryUsed":"","memorySize":"","invocationId":"","instanceId":"","concurrency":""},{"projectId":"prj_TEhZ3iXh2MfgelKntnyiJGpEFO9P","TimeUTC":"2025-12-12 14:20:08","timestampInMs":1765549208374,"requestPath":"api.gaiyatime.com/api/quota-status","requestMethod":"GET","requestQueryString":"user_id=f76fae0e-1e5b-40f1-9c8d-0d138aa65639&user_tier=pro","responseStatusCode":200,"requestId":"r8wxh-1765549206367-818f6cddeb05","requestUserAgent":"python-requests/2.32.4","environment":"production","branch":"main","vercelCache":"MISS","host":"api.gaiyatime.com","deploymentDomain":"api.gaiyatime.com","deploymentId":"dpl_2aMNxyLN1UYnCCzhMVrg1pooffv1","traceId":"","sessionId":"","type":"serverless","function":"/api/quota-status","level":"error","message":"Returning quota: {'remaining': {'daily_plan': 17, 'weekly_report': 10, 'chat': 100}, 'user_tier': 'pro'}","durationMs":"","region":"","maxMemoryUsed":"","memorySize":"","invocationId":"","instanceId":"","concurrency":""},{"projectId":"prj_TEhZ3iXh2MfgelKntnyiJGpEFO9P","TimeUTC":"2025-12-12 14:20:08","timestampInMs":1765549208374,"requestPath":"api.gaiyatime.com/api/quota-status","requestMethod":"GET","requestQueryString":"user_id=f76fae0e-1e5b-40f1-9c8d-0d138aa65639&user_tier=pro","responseStatusCode":200,"requestId":"r8wxh-1765549206367-818f6cddeb05","requestUserAgent":"python-requests/2.32.4","environment":"production","branch":"main","vercelCache":"MISS","host":"api.gaiyatime.com","deploymentDomain":"api.gaiyatime.com","deploymentId":"dpl_2aMNxyLN1UYnCCzhMVrg1pooffv1","traceId":"","sessionId":"","type":"serverless","function":"/api/quota-status","level":"info","message":"127.0.0.1 - - [12/Dec/2025 14:20:08] \"GET /api/quota-status?user_id=f76fae0e-1e5b-40f1-9c8d-0d138aa65639&user_tier=pro HTTP/1.1\" 200 -","durationMs":"","region":"","maxMemoryUsed":"","memorySize":"","invocationId":"","instanceId":"","concurrency":""},{"projectId":"prj_TEhZ3iXh2MfgelKntnyiJGpEFO9P","TimeUTC":"2025-12-12 14:20:06","timestampInMs":1765549206367,"requestPath":"api.gaiyatime.com/api/quota-status","requestMethod":"GET","requestQueryString":"user_id=f76fae0e-1e5b-40f1-9c8d-0d138aa65639&user_tier=pro","responseStatusCode":200,"requestId":"r8wxh-1765549206367-818f6cddeb05","requestUserAgent":"python-requests/2.32.4","environment":"production","branch":"main","vercelCache":"MISS","host":"api.gaiyatime.com","deploymentDomain":"api.gaiyatime.com","deploymentId":"dpl_2aMNxyLN1UYnCCzhMVrg1pooffv1","traceId":"","sessionId":"","type":"serverless","function":"/api/quota-status","level":"","message":"","durationMs":1958,"region":"iad1","maxMemoryUsed":275,"memorySize":2048,"invocationId":"01KC9EXTJ10TQE6RKANC70N344","instanceId":"SolRvrylshif","concurrency":4},{"projectId":"prj_TEhZ3iXh2MfgelKntnyiJGpEFO9P","TimeUTC":"2025-12-12 14:20:06","timestampInMs":1765549206112,"requestPath":"api.gaiyatime.com/api/quota-status","requestMethod":"GET","requestQueryString":"user_id=f76fae0e-1e5b-40f1-9c8d-0d138aa65639&user_tier=pro","responseStatusCode":200,"requestId":"kdxlm-1765549206036-46196db0f69c","requestUserAgent":"python-requests/2.32.4","environment":"production","branch":"main","vercelCache":"MISS","host":"api.gaiyatime.com","deploymentDomain":"api.gaiyatime.com","deploymentId":"dpl_2aMNxyLN1UYnCCzhMVrg1pooffv1","traceId":"","sessionId":"","type":"serverless","function":"/api/quota-status","level":"error","message":"Quota status function called","durationMs":"","region":"","maxMemoryUsed":"","memorySize":"","invocationId":"","instanceId":"","concurrency":""},{"projectId":"prj_TEhZ3iXh2MfgelKntnyiJGpEFO9P","TimeUTC":"2025-12-12 14:20:06","timestampInMs":1765549206112,"requestPath":"api.gaiyatime.com/api/quota-status","requestMethod":"GET","requestQueryString":"user_id=f76fae0e-1e5b-40f1-9c8d-0d138aa65639&user_tier=pro","responseStatusCode":200,"requestId":"kdxlm-1765549206036-46196db0f69c","requestUserAgent":"python-requests/2.32.4","environment":"production","branch":"main","vercelCache":"MISS","host":"api.gaiyatime.com","deploymentDomain":"api.gaiyatime.com","deploymentId":"dpl_2aMNxyLN1UYnCCzhMVrg1pooffv1","traceId":"","sessionId":"","type":"serverless","function":"/api/quota-status","level":"error","message":"User: f76fae0e-1e5b-40f1-9c8d-0d138aa65639, Tier: pro","durationMs":"","region":"","maxMemoryUsed":"","memorySize":"","invocationId":"","instanceId":"","concurrency":""},{"projectId":"prj_TEhZ3iXh2MfgelKntnyiJGpEFO9P","TimeUTC":"2025-12-12 14:20:06","timestampInMs":1765549206120,"requestPath":"api.gaiyatime.com/api/quota-status","requestMethod":"GET","requestQueryString":"user_id=f76fae0e-1e5b-40f1-9c8d-0d138aa65639&user_tier=pro","responseStatusCode":200,"requestId":"kdxlm-1765549206036-46196db0f69c","requestUserAgent":"python-requests/2.32.4","environment":"production","branch":"main","vercelCache":"MISS","host":"api.gaiyatime.com","deploymentDomain":"api.gaiyatime.com","deploymentId":"dpl_2aMNxyLN1UYnCCzhMVrg1pooffv1","traceId":"","sessionId":"","type":"serverless","function":"/api/quota-status","level":"error","message":"Supabase client initialized successfully","durationMs":"","region":"","maxMemoryUsed":"","memorySize":"","invocationId":"","instanceId":"","concurrency":""},{"projectId":"prj_TEhZ3iXh2MfgelKntnyiJGpEFO9P","TimeUTC":"2025-12-12 14:20:06","timestampInMs":1765549206953,"requestPath":"api.gaiyatime.com/api/quota-status","requestMethod":"GET","requestQueryString":"user_id=f76fae0e-1e5b-40f1-9c8d-0d138aa65639&user_tier=pro","responseStatusCode":200,"requestId":"kdxlm-1765549206036-46196db0f69c","requestUserAgent":"python-requests/2.32.4","environment":"production","branch":"main","vercelCache":"MISS","host":"api.gaiyatime.com","deploymentDomain":"api.gaiyatime.com","deploymentId":"dpl_2aMNxyLN1UYnCCzhMVrg1pooffv1","traceId":"","sessionId":"","type":"serverless","function":"/api/quota-status","level":"info","message":"HTTP Request: GET https://qpgypaxwjgcirssydgqh.supabase.co/rest/v1/user_quotas?select=%2A&user_id=eq.f76fae0e-1e5b-40f1-9c8d-0d138aa65639 \"HTTP/2 200 OK\"","durationMs":"","region":"","maxMemoryUsed":"","memorySize":"","invocationId":"","instanceId":"","concurrency":""},{"projectId":"prj_TEhZ3iXh2MfgelKntnyiJGpEFO9P","TimeUTC":"2025-12-12 14:20:06","timestampInMs":1765549206954,"requestPath":"api.gaiyatime.com/api/quota-status","requestMethod":"GET","requestQueryString":"user_id=f76fae0e-1e5b-40f1-9c8d-0d138aa65639&user_tier=pro","responseStatusCode":200,"requestId":"kdxlm-1765549206036-46196db0f69c","requestUserAgent":"python-requests/2.32.4","environment":"production","branch":"main","vercelCache":"MISS","host":"api.gaiyatime.com","deploymentDomain":"api.gaiyatime.com","deploymentId":"dpl_2aMNxyLN1UYnCCzhMVrg1pooffv1","traceId":"","sessionId":"","type":"serverless","function":"/api/quota-status","level":"error","message":"User tier changed: free -> pro, updating...","durationMs":"","region":"","maxMemoryUsed":"","memorySize":"","invocationId":"","instanceId":"","concurrency":""},{"projectId":"prj_TEhZ3iXh2MfgelKntnyiJGpEFO9P","TimeUTC":"2025-12-12 14:20:07","timestampInMs":1765549207770,"requestPath":"api.gaiyatime.com/api/quota-status","requestMethod":"GET","requestQueryString":"user_id=f76fae0e-1e5b-40f1-9c8d-0d138aa65639&user_tier=pro","responseStatusCode":200,"requestId":"kdxlm-1765549206036-46196db0f69c","requestUserAgent":"python-requests/2.32.4","environment":"production","branch":"main","vercelCache":"MISS","host":"api.gaiyatime.com","deploymentDomain":"api.gaiyatime.com","deploymentId":"dpl_2aMNxyLN1UYnCCzhMVrg1pooffv1","traceId":"","sessionId":"","type":"serverless","function":"/api/quota-status","level":"info","message":"HTTP Request: PATCH https://qpgypaxwjgcirssydgqh.supabase.co/rest/v1/user_quotas?user_id=eq.f76fae0e-1e5b-40f1-9c8d-0d138aa65639 \"HTTP/2 200 OK\"","durationMs":"","region":"","maxMemoryUsed":"","memorySize":"","invocationId":"","instanceId":"","concurrency":""},{"projectId":"prj_TEhZ3iXh2MfgelKntnyiJGpEFO9P","TimeUTC":"2025-12-12 14:20:07","timestampInMs":1765549207770,"requestPath":"api.gaiyatime.com/api/quota-status","requestMethod":"GET","requestQueryString":"user_id=f76fae0e-1e5b-40f1-9c8d-0d138aa65639&user_tier=pro","responseStatusCode":200,"requestId":"kdxlm-1765549206036-46196db0f69c","requestUserAgent":"python-requests/2.32.4","environment":"production","branch":"main","vercelCache":"MISS","host":"api.gaiyatime.com","deploymentDomain":"api.gaiyatime.com","deploymentId":"dpl_2aMNxyLN1UYnCCzhMVrg1pooffv1","traceId":"","sessionId":"","type":"serverless","function":"/api/quota-status","level":"error","message":"Updated user tier from free to pro","durationMs":"","region":"","maxMemoryUsed":"","memorySize":"","invocationId":"","instanceId":"","concurrency":""},{"projectId":"prj_TEhZ3iXh2MfgelKntnyiJGpEFO9P","TimeUTC":"2025-12-12 14:20:08","timestampInMs":1765549208073,"requestPath":"api.gaiyatime.com/api/quota-status","requestMethod":"GET","requestQueryString":"user_id=f76fae0e-1e5b-40f1-9c8d-0d138aa65639&user_tier=pro","responseStatusCode":200,"requestId":"kdxlm-1765549206036-46196db0f69c","requestUserAgent":"python-requests/2.32.4","environment":"production","branch":"main","vercelCache":"MISS","host":"api.gaiyatime.com","deploymentDomain":"api.gaiyatime.com","deploymentId":"dpl_2aMNxyLN1UYnCCzhMVrg1pooffv1","traceId":"","sessionId":"","type":"serverless","function":"/api/quota-status","level":"info","message":"HTTP Request: GET https://qpgypaxwjgcirssydgqh.supabase.co/rest/v1/user_quotas?select=%2A&user_id=eq.f76fae0e-1e5b-40f1-9c8d-0d138aa65639 \"HTTP/2 200 OK\"","durationMs":"","region":"","maxMemoryUsed":"","memorySize":"","invocationId":"","instanceId":"","concurrency":""},{"projectId":"prj_TEhZ3iXh2MfgelKntnyiJGpEFO9P","TimeUTC":"2025-12-12 14:20:08","timestampInMs":1765549208074,"requestPath":"api.gaiyatime.com/api/quota-status","requestMethod":"GET","requestQueryString":"user_id=f76fae0e-1e5b-40f1-9c8d-0d138aa65639&user_tier=pro","responseStatusCode":200,"requestId":"kdxlm-1765549206036-46196db0f69c","requestUserAgent":"python-requests/2.32.4","environment":"production","branch":"main","vercelCache":"MISS","host":"api.gaiyatime.com","deploymentDomain":"api.gaiyatime.com","deploymentId":"dpl_2aMNxyLN1UYnCCzhMVrg1pooffv1","traceId":"","sessionId":"","type":"serverless","function":"/api/quota-status","level":"error","message":"Returning quota: {'remaining': {'daily_plan': 17, 'weekly_report': 10, 'chat': 100}, 'user_tier': 'pro'}","durationMs":"","region":"","maxMemoryUsed":"","memorySize":"","invocationId":"","instanceId":"","concurrency":""},{"projectId":"prj_TEhZ3iXh2MfgelKntnyiJGpEFO9P","TimeUTC":"2025-12-12 14:20:08","timestampInMs":1765549208075,"requestPath":"api.gaiyatime.com/api/quota-status","requestMethod":"GET","requestQueryString":"user_id=f76fae0e-1e5b-40f1-9c8d-0d138aa65639&user_tier=pro","responseStatusCode":200,"requestId":"kdxlm-1765549206036-46196db0f69c","requestUserAgent":"python-requests/2.32.4","environment":"production","branch":"main","vercelCache":"MISS","host":"api.gaiyatime.com","deploymentDomain":"api.gaiyatime.com","deploymentId":"dpl_2aMNxyLN1UYnCCzhMVrg1pooffv1","traceId":"","sessionId":"","type":"serverless","function":"/api/quota-status","level":"info","message":"127.0.0.1 - - [12/Dec/2025 14:20:08] \"GET /api/quota-status?user_id=f76fae0e-1e5b-40f1-9c8d-0d138aa65639&user_tier=pro HTTP/1.1\" 200 -","durationMs":"","region":"","maxMemoryUsed":"","memorySize":"","invocationId":"","instanceId":"","concurrency":""},{"projectId":"prj_TEhZ3iXh2MfgelKntnyiJGpEFO9P","TimeUTC":"2025-12-12 14:20:06","timestampInMs":1765549206036,"requestPath":"api.gaiyatime.com/api/quota-status","requestMethod":"GET","requestQueryString":"user_id=f76fae0e-1e5b-40f1-9c8d-0d138aa65639&user_tier=pro","responseStatusCode":200,"requestId":"kdxlm-1765549206036-46196db0f69c","requestUserAgent":"python-requests/2.32.4","environment":"production","branch":"main","vercelCache":"MISS","host":"api.gaiyatime.com","deploymentDomain":"api.gaiyatime.com","deploymentId":"dpl_2aMNxyLN1UYnCCzhMVrg1pooffv1","traceId":"","sessionId":"","type":"serverless","function":"/api/quota-status","level":"","message":"","durationMs":1968,"region":"iad1","maxMemoryUsed":275,"memorySize":2048,"invocationId":"01KC9EXTJ10TQE6RKANC70N344","instanceId":"SolRvrylshif","concurrency":4},{"projectId":"prj_TEhZ3iXh2MfgelKntnyiJGpEFO9P","TimeUTC":"2025-12-12 14:19:08","timestampInMs":1765549148691,"requestPath":"api.gaiyatime.com/api/plan-tasks","requestMethod":"POST","requestQueryString":"","responseStatusCode":200,"requestId":"vkv5m-1765549148102-affa6ff5c539","requestUserAgent":"python-requests/2.32.4","environment":"production","branch":"main","vercelCache":"MISS","host":"api.gaiyatime.com","deploymentDomain":"api.gaiyatime.com","deploymentId":"dpl_2aMNxyLN1UYnCCzhMVrg1pooffv1","traceId":"","sessionId":"","type":"serverless","function":"/api/plan-tasks","level":"error","message":"Plan tasks function called","durationMs":"","region":"","maxMemoryUsed":"","memorySize":"","invocationId":"","instanceId":"","concurrency":""},{"projectId":"prj_TEhZ3iXh2MfgelKntnyiJGpEFO9P","TimeUTC":"2025-12-12 14:19:08","timestampInMs":1765549148692,"requestPath":"api.gaiyatime.com/api/plan-tasks","requestMethod":"POST","requestQueryString":"","responseStatusCode":200,"requestId":"vkv5m-1765549148102-affa6ff5c539","requestUserAgent":"python-requests/2.32.4","environment":"production","branch":"main","vercelCache":"MISS","host":"api.gaiyatime.com","deploymentDomain":"api.gaiyatime.com","deploymentId":"dpl_2aMNxyLN1UYnCCzhMVrg1pooffv1","traceId":"","sessionId":"","type":"serverless","function":"/api/plan-tasks","level":"error","message":"Request body: {\"user_id\": \"f76fae0e-1e5b-40f1-9c8d-0d138aa65639\", \"input\": \"\\u6211\\u9700\\u8981\\u4e00\\u4e2a\\u8f7b\\u677e\\u7684\\u5468\\u672b/\\u4f11\\u606f\\u65e5\\u4efb\\u52a1\\u8ba1\\u5212\\u3002\\u5305\\u62ec:\\n- 9:00 \\u81ea\\","durationMs":"","region":"","maxMemoryUsed":"","memorySize":"","invocationId":"","instanceId":"","concurrency":""},{"projectId":"prj_TEhZ3iXh2MfgelKntnyiJGpEFO9P","TimeUTC":"2025-12-12 14:19:09","timestampInMs":1765549149037,"requestPath":"api.gaiyatime.com/api/plan-tasks","requestMethod":"POST","requestQueryString":"","responseStatusCode":200,"requestId":"vkv5m-1765549148102-affa6ff5c539","requestUserAgent":"python-requests/2.32.4","environment":"production","branch":"main","vercelCache":"MISS","host":"api.gaiyatime.com","deploymentDomain":"api.gaiyatime.com","deploymentId":"dpl_2aMNxyLN1UYnCCzhMVrg1pooffv1","traceId":"","sessionId":"","type":"serverless","function":"/api/plan-tasks","level":"error","message":"Supabase client initialized successfully","durationMs":"","region":"","maxMemoryUsed":"","memorySize":"","invocationId":"","instanceId":"","concurrency":""},{"projectId":"prj_TEhZ3iXh2MfgelKntnyiJGpEFO9P","TimeUTC":"2025-12-12 14:19:09","timestampInMs":1765549149880,"requestPath":"api.gaiyatime.com/api/plan-tasks","requestMethod":"POST","requestQueryString":"","responseStatusCode":200,"requestId":"vkv5m-1765549148102-affa6ff5c539","requestUserAgent":"python-requests/2.32.4","environment":"production","branch":"main","vercelCache":"MISS","host":"api.gaiyatime.com","deploymentDomain":"api.gaiyatime.com","deploymentId":"dpl_2aMNxyLN1UYnCCzhMVrg1pooffv1","traceId":"","sessionId":"","type":"serverless","function":"/api/plan-tasks","level":"info","message":"HTTP Request: GET https://qpgypaxwjgcirssydgqh.supabase.co/rest/v1/user_quotas?select=%2A&user_id=eq.f76fae0e-1e5b-40f1-9c8d-0d138aa65639 \"HTTP/2 200 OK\"","durationMs":"","region":"","maxMemoryUsed":"","memorySize":"","invocationId":"","instanceId":"","concurrency":""},{"projectId":"prj_TEhZ3iXh2MfgelKntnyiJGpEFO9P","TimeUTC":"2025-12-12 14:19:09","timestampInMs":1765549149882,"requestPath":"api.gaiyatime.com/api/plan-tasks","requestMethod":"POST","requestQueryString":"","responseStatusCode":200,"requestId":"vkv5m-1765549148102-affa6ff5c539","requestUserAgent":"python-requests/2.32.4","environment":"production","branch":"main","vercelCache":"MISS","host":"api.gaiyatime.com","deploymentDomain":"api.gaiyatime.com","deploymentId":"dpl_2aMNxyLN1UYnCCzhMVrg1pooffv1","traceId":"","sessionId":"","type":"serverless","function":"/api/plan-tasks","level":"error","message":"Calling API: https://api.tu-zi.com/v1/chat/completions","durationMs":"","region":"","maxMemoryUsed":"","memorySize":"","invocationId":"","instanceId":"","concurrency":""},{"projectId":"prj_TEhZ3iXh2MfgelKntnyiJGpEFO9P","TimeUTC":"2025-12-12 14:19:55","timestampInMs":1765549195397,"requestPath":"api.gaiyatime.com/api/plan-tasks","requestMethod":"POST","requestQueryString":"","responseStatusCode":200,"requestId":"vkv5m-1765549148102-affa6ff5c539","requestUserAgent":"python-requests/2.32.4","environment":"production","branch":"main","vercelCache":"MISS","host":"api.gaiyatime.com","deploymentDomain":"api.gaiyatime.com","deploymentId":"dpl_2aMNxyLN1UYnCCzhMVrg1pooffv1","traceId":"","sessionId":"","type":"serverless","function":"/api/plan-tasks","level":"error","message":"API response status: 200","durationMs":"","region":"","maxMemoryUsed":"","memorySize":"","invocationId":"","instanceId":"","concurrency":""},{"projectId":"prj_TEhZ3iXh2MfgelKntnyiJGpEFO9P","TimeUTC":"2025-12-12 14:19:55","timestampInMs":1765549195398,"requestPath":"api.gaiyatime.com/api/plan-tasks","requestMethod":"POST","requestQueryString":"","responseStatusCode":200,"requestId":"vkv5m-1765549148102-affa6ff5c539","requestUserAgent":"python-requests/2.32.4","environment":"production","branch":"main","vercelCache":"MISS","host":"api.gaiyatime.com","deploymentDomain":"api.gaiyatime.com","deploymentId":"dpl_2aMNxyLN1UYnCCzhMVrg1pooffv1","traceId":"","sessionId":"","type":"serverless","function":"/api/plan-tasks","level":"error","message":"Token usage: prompt=839, completion=2504, total=3343","durationMs":"","region":"","maxMemoryUsed":"","memorySize":"","invocationId":"","instanceId":"","concurrency":""},{"projectId":"prj_TEhZ3iXh2MfgelKntnyiJGpEFO9P","TimeUTC":"2025-12-12 14:19:56","timestampInMs":1765549196208,"requestPath":"api.gaiyatime.com/api/plan-tasks","requestMethod":"POST","requestQueryString":"","responseStatusCode":200,"requestId":"vkv5m-1765549148102-affa6ff5c539","requestUserAgent":"python-requests/2.32.4","environment":"production","branch":"main","vercelCache":"MISS","host":"api.gaiyatime.com","deploymentDomain":"api.gaiyatime.com","deploymentId":"dpl_2aMNxyLN1UYnCCzhMVrg1pooffv1","traceId":"","sessionId":"","type":"serverless","function":"/api/plan-tasks","level":"info","message":"HTTP Request: GET https://qpgypaxwjgcirssydgqh.supabase.co/rest/v1/user_quotas?select=%2A&user_id=eq.f76fae0e-1e5b-40f1-9c8d-0d138aa65639 \"HTTP/2 200 OK\"","durationMs":"","region":"","maxMemoryUsed":"","memorySize":"","invocationId":"","instanceId":"","concurrency":""},{"projectId":"prj_TEhZ3iXh2MfgelKntnyiJGpEFO9P","TimeUTC":"2025-12-12 14:19:56","timestampInMs":1765549196209,"requestPath":"api.gaiyatime.com/api/plan-tasks","requestMethod":"POST","requestQueryString":"","responseStatusCode":200,"requestId":"vkv5m-1765549148102-affa6ff5c539","requestUserAgent":"python-requests/2.32.4","environment":"production","branch":"main","vercelCache":"MISS","host":"api.gaiyatime.com","deploymentDomain":"api.gaiyatime.com","deploymentId":"dpl_2aMNxyLN1UYnCCzhMVrg1pooffv1","traceId":"","sessionId":"","type":"serverless","function":"/api/plan-tasks","level":"error","message":"User tier changed: pro -> free, updating...","durationMs":"","region":"","maxMemoryUsed":"","memorySize":"","invocationId":"","instanceId":"","concurrency":""},{"projectId":"prj_TEhZ3iXh2MfgelKntnyiJGpEFO9P","TimeUTC":"2025-12-12 14:19:56","timestampInMs":1765549196488,"requestPath":"api.gaiyatime.com/api/plan-tasks","requestMethod":"POST","requestQueryString":"","responseStatusCode":200,"requestId":"vkv5m-1765549148102-affa6ff5c539","requestUserAgent":"python-requests/2.32.4","environment":"production","branch":"main","vercelCache":"MISS","host":"api.gaiyatime.com","deploymentDomain":"api.gaiyatime.com","deploymentId":"dpl_2aMNxyLN1UYnCCzhMVrg1pooffv1","traceId":"","sessionId":"","type":"serverless","function":"/api/plan-tasks","level":"info","message":"HTTP Request: PATCH https://qpgypaxwjgcirssydgqh.supabase.co/rest/v1/user_quotas?user_id=eq.f76fae0e-1e5b-40f1-9c8d-0d138aa65639 \"HTTP/2 200 OK\"","durationMs":"","region":"","maxMemoryUsed":"","memorySize":"","invocationId":"","instanceId":"","concurrency":""},{"projectId":"prj_TEhZ3iXh2MfgelKntnyiJGpEFO9P","TimeUTC":"2025-12-12 14:19:56","timestampInMs":1765549196489,"requestPath":"api.gaiyatime.com/api/plan-tasks","requestMethod":"POST","requestQueryString":"","responseStatusCode":200,"requestId":"vkv5m-1765549148102-affa6ff5c539","requestUserAgent":"python-requests/2.32.4","environment":"production","branch":"main","vercelCache":"MISS","host":"api.gaiyatime.com","deploymentDomain":"api.gaiyatime.com","deploymentId":"dpl_2aMNxyLN1UYnCCzhMVrg1pooffv1","traceId":"","sessionId":"","type":"serverless","function":"/api/plan-tasks","level":"error","message":"Updated user tier from pro to free","durationMs":"","region":"","maxMemoryUsed":"","memorySize":"","invocationId":"","instanceId":"","concurrency":""},{"projectId":"prj_TEhZ3iXh2MfgelKntnyiJGpEFO9P","TimeUTC":"2025-12-12 14:19:56","timestampInMs":1765549196765,"requestPath":"api.gaiyatime.com/api/plan-tasks","requestMethod":"POST","requestQueryString":"","responseStatusCode":200,"requestId":"vkv5m-1765549148102-affa6ff5c539","requestUserAgent":"python-requests/2.32.4","environment":"production","branch":"main","vercelCache":"MISS","host":"api.gaiyatime.com","deploymentDomain":"api.gaiyatime.com","deploymentId":"dpl_2aMNxyLN1UYnCCzhMVrg1pooffv1","traceId":"","sessionId":"","type":"serverless","function":"/api/plan-tasks","level":"info","message":"HTTP Request: GET https://qpgypaxwjgcirssydgqh.supabase.co/rest/v1/user_quotas?select=%2A&user_id=eq.f76fae0e-1e5b-40f1-9c8d-0d138aa65639 \"HTTP/2 200 OK\"","durationMs":"","region":"","maxMemoryUsed":"","memorySize":"","invocationId":"","instanceId":"","concurrency":""},{"projectId":"prj_TEhZ3iXh2MfgelKntnyiJGpEFO9P","TimeUTC":"2025-12-12 14:19:56","timestampInMs":1765549196765,"requestPath":"api.gaiyatime.com/api/plan-tasks","requestMethod":"POST","requestQueryString":"","responseStatusCode":200,"requestId":"vkv5m-1765549148102-affa6ff5c539","requestUserAgent":"python-requests/2.32.4","environment":"production","branch":"main","vercelCache":"MISS","host":"api.gaiyatime.com","deploymentDomain":"api.gaiyatime.com","deploymentId":"dpl_2aMNxyLN1UYnCCzhMVrg1pooffv1","traceId":"","sessionId":"","type":"serverless","function":"/api/plan-tasks","level":"error","message":"Failed to use quota: {'success': False, 'error': 'Quota exceeded', 'remaining': 0, 'requested': 1}","durationMs":"","region":"","maxMemoryUsed":"","memorySize":"","invocationId":"","instanceId":"","concurrency":""},{"projectId":"prj_TEhZ3iXh2MfgelKntnyiJGpEFO9P","TimeUTC":"2025-12-12 14:19:56","timestampInMs":1765549196765,"requestPath":"api.gaiyatime.com/api/plan-tasks","requestMethod":"POST","requestQueryString":"","responseStatusCode":200,"requestId":"vkv5m-1765549148102-affa6ff5c539","requestUserAgent":"python-requests/2.32.4","environment":"production","branch":"main","vercelCache":"MISS","host":"api.gaiyatime.com","deploymentDomain":"api.gaiyatime.com","deploymentId":"dpl_2aMNxyLN1UYnCCzhMVrg1pooffv1","traceId":"","sessionId":"","type":"serverless","function":"/api/plan-tasks","level":"error","message":"Successfully generated 10 tasks","durationMs":"","region":"","maxMemoryUsed":"","memorySize":"","invocationId":"","instanceId":"","concurrency":""},{"projectId":"prj_TEhZ3iXh2MfgelKntnyiJGpEFO9P","TimeUTC":"2025-12-12 14:19:56","timestampInMs":1765549196765,"requestPath":"api.gaiyatime.com/api/plan-tasks","requestMethod":"POST","requestQueryString":"","responseStatusCode":200,"requestId":"vkv5m-1765549148102-affa6ff5c539","requestUserAgent":"python-requests/2.32.4","environment":"production","branch":"main","vercelCache":"MISS","host":"api.gaiyatime.com","deploymentDomain":"api.gaiyatime.com","deploymentId":"dpl_2aMNxyLN1UYnCCzhMVrg1pooffv1","traceId":"","sessionId":"","type":"serverless","function":"/api/plan-tasks","level":"info","message":"127.0.0.1 - - [12/Dec/2025 14:19:56] \"POST /api/plan-tasks HTTP/1.1\" 200 -","durationMs":"","region":"","maxMemoryUsed":"","memorySize":"","invocationId":"","instanceId":"","concurrency":""},{"projectId":"prj_TEhZ3iXh2MfgelKntnyiJGpEFO9P","TimeUTC":"2025-12-12 14:19:08","timestampInMs":1765549148102,"requestPath":"api.gaiyatime.com/api/plan-tasks","requestMethod":"POST","requestQueryString":"","responseStatusCode":200,"requestId":"vkv5m-1765549148102-affa6ff5c539","requestUserAgent":"python-requests/2.32.4","environment":"production","branch":"main","vercelCache":"MISS","host":"api.gaiyatime.com","deploymentDomain":"api.gaiyatime.com","deploymentId":"dpl_2aMNxyLN1UYnCCzhMVrg1pooffv1","traceId":"","sessionId":"","type":"serverless","function":"/api/plan-tasks","level":"","message":"","durationMs":48084,"region":"iad1","maxMemoryUsed":273,"memorySize":2048,"invocationId":"01KC9EW2FT8CDDGCYCBT64N327","instanceId":"PmzmqN5l28tJ","concurrency":1},{"projectId":"prj_TEhZ3iXh2MfgelKntnyiJGpEFO9P","TimeUTC":"2025-12-12 14:19:01","timestampInMs":1765549141445,"requestPath":"api.gaiyatime.com/api/quota-status","requestMethod":"GET","requestQueryString":"user_id=f76fae0e-1e5b-40f1-9c8d-0d138aa65639&user_tier=pro","responseStatusCode":200,"requestId":"fb9xb-1765549141396-1b17938099db","requestUserAgent":"python-requests/2.32.4","environment":"production","branch":"main","vercelCache":"MISS","host":"api.gaiyatime.com","deploymentDomain":"api.gaiyatime.com","deploymentId":"dpl_2aMNxyLN1UYnCCzhMVrg1pooffv1","traceId":"","sessionId":"","type":"serverless","function":"/api/quota-status","level":"error","message":"Quota status function called","durationMs":"","region":"","maxMemoryUsed":"","memorySize":"","invocationId":"","instanceId":"","concurrency":""},{"projectId":"prj_TEhZ3iXh2MfgelKntnyiJGpEFO9P","TimeUTC":"2025-12-12 14:19:01","timestampInMs":1765549141445,"requestPath":"api.gaiyatime.com/api/quota-status","requestMethod":"GET","requestQueryString":"user_id=f76fae0e-1e5b-40f1-9c8d-0d138aa65639&user_tier=pro","responseStatusCode":200,"requestId":"fb9xb-1765549141396-1b17938099db","requestUserAgent":"python-requests/2.32.4","environment":"production","branch":"main","vercelCache":"MISS","host":"api.gaiyatime.com","deploymentDomain":"api.gaiyatime.com","deploymentId":"dpl_2aMNxyLN1UYnCCzhMVrg1pooffv1","traceId":"","sessionId":"","type":"serverless","function":"/api/quota-status","level":"error","message":"User: f76fae0e-1e5b-40f1-9c8d-0d138aa65639, Tier: pro","durationMs":"","region":"","maxMemoryUsed":"","memorySize":"","invocationId":"","instanceId":"","concurrency":""},{"projectId":"prj_TEhZ3iXh2MfgelKntnyiJGpEFO9P","TimeUTC":"2025-12-12 14:19:01","timestampInMs":1765549141455,"requestPath":"api.gaiyatime.com/api/quota-status","requestMethod":"GET","requestQueryString":"user_id=f76fae0e-1e5b-40f1-9c8d-0d138aa65639&user_tier=pro","responseStatusCode":200,"requestId":"fb9xb-1765549141396-1b17938099db","requestUserAgent":"python-requests/2.32.4","environment":"production","branch":"main","vercelCache":"MISS","host":"api.gaiyatime.com","deploymentDomain":"api.gaiyatime.com","deploymentId":"dpl_2aMNxyLN1UYnCCzhMVrg1pooffv1","traceId":"","sessionId":"","type":"serverless","function":"/api/quota-status","level":"error","message":"Supabase client initialized successfully","durationMs":"","region":"","maxMemoryUsed":"","memorySize":"","invocationId":"","instanceId":"","concurrency":""},{"projectId":"prj_TEhZ3iXh2MfgelKntnyiJGpEFO9P","TimeUTC":"2025-12-12 14:19:02","timestampInMs":1765549142302,"requestPath":"api.gaiyatime.com/api/quota-status","requestMethod":"GET","requestQueryString":"user_id=f76fae0e-1e5b-40f1-9c8d-0d138aa65639&user_tier=pro","responseStatusCode":200,"requestId":"fb9xb-1765549141396-1b17938099db","requestUserAgent":"python-requests/2.32.4","environment":"production","branch":"main","vercelCache":"MISS","host":"api.gaiyatime.com","deploymentDomain":"api.gaiyatime.com","deploymentId":"dpl_2aMNxyLN1UYnCCzhMVrg1pooffv1","traceId":"","sessionId":"","type":"serverless","function":"/api/quota-status","level":"info","message":"HTTP Request: GET https://qpgypaxwjgcirssydgqh.supabase.co/rest/v1/user_quotas?select=%2A&user_id=eq.f76fae0e-1e5b-40f1-9c8d-0d138aa65639 \"HTTP/2 200 OK\"","durationMs":"","region":"","maxMemoryUsed":"","memorySize":"","invocationId":"","instanceId":"","concurrency":""},{"projectId":"prj_TEhZ3iXh2MfgelKntnyiJGpEFO9P","TimeUTC":"2025-12-12 14:19:02","timestampInMs":1765549142303,"requestPath":"api.gaiyatime.com/api/quota-status","requestMethod":"GET","requestQueryString":"user_id=f76fae0e-1e5b-40f1-9c8d-0d138aa65639&user_tier=pro","responseStatusCode":200,"requestId":"fb9xb-1765549141396-1b17938099db","requestUserAgent":"python-requests/2.32.4","environment":"production","branch":"main","vercelCache":"MISS","host":"api.gaiyatime.com","deploymentDomain":"api.gaiyatime.com","deploymentId":"dpl_2aMNxyLN1UYnCCzhMVrg1pooffv1","traceId":"","sessionId":"","type":"serverless","function":"/api/quota-status","level":"error","message":"Returning quota: {'remaining': {'daily_plan': 17, 'weekly_report': 10, 'chat': 100}, 'user_tier': 'pro'}","durationMs":"","region":"","maxMemoryUsed":"","memorySize":"","invocationId":"","instanceId":"","concurrency":""},{"projectId":"prj_TEhZ3iXh2MfgelKntnyiJGpEFO9P","TimeUTC":"2025-12-12 14:19:02","timestampInMs":1765549142303,"requestPath":"api.gaiyatime.com/api/quota-status","requestMethod":"GET","requestQueryString":"user_id=f76fae0e-1e5b-40f1-9c8d-0d138aa65639&user_tier=pro","responseStatusCode":200,"requestId":"fb9xb-1765549141396-1b17938099db","requestUserAgent":"python-requests/2.32.4","environment":"production","branch":"main","vercelCache":"MISS","host":"api.gaiyatime.com","deploymentDomain":"api.gaiyatime.com","deploymentId":"dpl_2aMNxyLN1UYnCCzhMVrg1pooffv1","traceId":"","sessionId":"","type":"serverless","function":"/api/quota-status","level":"info","message":"127.0.0.1 - - [12/Dec/2025 14:19:02] \"GET /api/quota-status?user_id=f76fae0e-1e5b-40f1-9c8d-0d138aa65639&user_tier=pro HTTP/1.1\" 200 -","durationMs":"","region":"","maxMemoryUsed":"","memorySize":"","invocationId":"","instanceId":"","concurrency":""},{"projectId":"prj_TEhZ3iXh2MfgelKntnyiJGpEFO9P","TimeUTC":"2025-12-12 14:19:01","timestampInMs":1765549141396,"requestPath":"api.gaiyatime.com/api/quota-status","requestMethod":"GET","requestQueryString":"user_id=f76fae0e-1e5b-40f1-9c8d-0d138aa65639&user_tier=pro","responseStatusCode":200,"requestId":"fb9xb-1765549141396-1b17938099db","requestUserAgent":"python-requests/2.32.4","environment":"production","branch":"main","vercelCache":"MISS","host":"api.gaiyatime.com","deploymentDomain":"api.gaiyatime.com","deploymentId":"dpl_2aMNxyLN1UYnCCzhMVrg1pooffv1","traceId":"","sessionId":"","type":"serverless","function":"/api/quota-status","level":"","message":"","durationMs":859,"region":"iad1","maxMemoryUsed":267,"memorySize":2048,"invocationId":"01KC9EVT2K69WBD6SKZ87AG39K","instanceId":"SolRvrylshif","concurrency":2},{"projectId":"prj_TEhZ3iXh2MfgelKntnyiJGpEFO9P","TimeUTC":"2025-12-12 14:19:00","timestampInMs":1765549140406,"requestPath":"api.gaiyatime.com/api/health","requestMethod":"GET","requestQueryString":"","responseStatusCode":200,"requestId":"ccpcg-1765549140182-4ed2a9bdbc10","requestUserAgent":"python-requests/2.32.4","environment":"production","branch":"main","vercelCache":"MISS","host":"api.gaiyatime.com","deploymentDomain":"api.gaiyatime.com","deploymentId":"dpl_2aMNxyLN1UYnCCzhMVrg1pooffv1","traceId":"","sessionId":"","type":"serverless","function":"/api/health","level":"error","message":"Health check function called","durationMs":"","region":"","maxMemoryUsed":"","memorySize":"","invocationId":"","instanceId":"","concurrency":""},{"projectId":"prj_TEhZ3iXh2MfgelKntnyiJGpEFO9P","TimeUTC":"2025-12-12 14:19:00","timestampInMs":1765549140406,"requestPath":"api.gaiyatime.com/api/health","requestMethod":"GET","requestQueryString":"","responseStatusCode":200,"requestId":"ccpcg-1765549140182-4ed2a9bdbc10","requestUserAgent":"python-requests/2.32.4","environment":"production","branch":"main","vercelCache":"MISS","host":"api.gaiyatime.com","deploymentDomain":"api.gaiyatime.com","deploymentId":"dpl_2aMNxyLN1UYnCCzhMVrg1pooffv1","traceId":"","sessionId":"","type":"serverless","function":"/api/health","level":"error","message":"Returning response: {'status': 'ok', 'timestamp': '2025-12-12T14:19:00.405726', 'service': 'GaiYa API Service (Vercel)', 'message': 'Health check successful'}","durationMs":"","region":"","maxMemoryUsed":"","memorySize":"","invocationId":"","instanceId":"","concurrency":""},{"projectId":"prj_TEhZ3iXh2MfgelKntnyiJGpEFO9P","TimeUTC":"2025-12-12 14:19:00","timestampInMs":1765549140406,"requestPath":"api.gaiyatime.com/api/health","requestMethod":"GET","requestQueryString":"","responseStatusCode":200,"requestId":"ccpcg-1765549140182-4ed2a9bdbc10","requestUserAgent":"python-requests/2.32.4","environment":"production","branch":"main","vercelCache":"MISS","host":"api.gaiyatime.com","deploymentDomain":"api.gaiyatime.com","deploymentId":"dpl_2aMNxyLN1UYnCCzhMVrg1pooffv1","traceId":"","sessionId":"","type":"serverless","function":"/api/health","level":"info","message":"127.0.0.1 - - [12/Dec/2025 14:19:00] \"GET /api/health HTTP/1.1\" 200 -","durationMs":"","region":"","maxMemoryUsed":"","memorySize":"","invocationId":"","instanceId":"","concurrency":""},{"projectId":"prj_TEhZ3iXh2MfgelKntnyiJGpEFO9P","TimeUTC":"2025-12-12 14:19:00","timestampInMs":1765549140182,"requestPath":"api.gaiyatime.com/api/health","requestMethod":"GET","requestQueryString":"","responseStatusCode":200,"requestId":"ccpcg-1765549140182-4ed2a9bdbc10","requestUserAgent":"python-requests/2.32.4","environment":"production","branch":"main","vercelCache":"MISS","host":"api.gaiyatime.com","deploymentDomain":"api.gaiyatime.com","deploymentId":"dpl_2aMNxyLN1UYnCCzhMVrg1pooffv1","traceId":"","sessionId":"","type":"serverless","function":"/api/health","level":"","message":"","durationMs":8,"region":"iad1","maxMemoryUsed":227,"memorySize":2048,"invocationId":"01KC9EVTCNEPM4B65447JP4J97","instanceId":"LAN4G2O7wMDO","concurrency":1},{"projectId":"prj_TEhZ3iXh2MfgelKntnyiJGpEFO9P","TimeUTC":"2025-12-12 14:19:00","timestampInMs":1765549140076,"requestPath":"api.gaiyatime.com/api/quota-status","requestMethod":"GET","requestQueryString":"user_id=f76fae0e-1e5b-40f1-9c8d-0d138aa65639&user_tier=pro","responseStatusCode":"","requestId":"4m8fd-1765549139692-d0ec2520f98a","requestUserAgent":"python-requests/2.32.4","environment":"production","branch":"main","vercelCache":"","host":"api.gaiyatime.com","deploymentDomain":"api.gaiyatime.com","deploymentId":"dpl_2aMNxyLN1UYnCCzhMVrg1pooffv1","traceId":"","sessionId":"","type":"serverless","function":"","level":"error","message":"Quota status function called","durationMs":"","region":"","maxMemoryUsed":"","memorySize":"","invocationId":"","instanceId":"","concurrency":""},{"projectId":"prj_TEhZ3iXh2MfgelKntnyiJGpEFO9P","TimeUTC":"2025-12-12 14:19:00","timestampInMs":1765549140076,"requestPath":"api.gaiyatime.com/api/quota-status","requestMethod":"GET","requestQueryString":"user_id=f76fae0e-1e5b-40f1-9c8d-0d138aa65639&user_tier=pro","responseStatusCode":"","requestId":"4m8fd-1765549139692-d0ec2520f98a","requestUserAgent":"python-requests/2.32.4","environment":"production","branch":"main","vercelCache":"","host":"api.gaiyatime.com","deploymentDomain":"api.gaiyatime.com","deploymentId":"dpl_2aMNxyLN1UYnCCzhMVrg1pooffv1","traceId":"","sessionId":"","type":"serverless","function":"","level":"error","message":"User: f76fae0e-1e5b-40f1-9c8d-0d138aa65639, Tier: pro","durationMs":"","region":"","maxMemoryUsed":"","memorySize":"","invocationId":"","instanceId":"","concurrency":""},{"projectId":"prj_TEhZ3iXh2MfgelKntnyiJGpEFO9P","TimeUTC":"2025-12-12 14:19:00","timestampInMs":1765549140444,"requestPath":"api.gaiyatime.com/api/quota-status","requestMethod":"GET","requestQueryString":"user_id=f76fae0e-1e5b-40f1-9c8d-0d138aa65639&user_tier=pro","responseStatusCode":"","requestId":"4m8fd-1765549139692-d0ec2520f98a","requestUserAgent":"python-requests/2.32.4","environment":"production","branch":"main","vercelCache":"","host":"api.gaiyatime.com","deploymentDomain":"api.gaiyatime.com","deploymentId":"dpl_2aMNxyLN1UYnCCzhMVrg1pooffv1","traceId":"","sessionId":"","type":"serverless","function":"","level":"error","message":"Supabase client initialized successfully","durationMs":"","region":"","maxMemoryUsed":"","memorySize":"","invocationId":"","instanceId":"","concurrency":""},{"projectId":"prj_TEhZ3iXh2MfgelKntnyiJGpEFO9P","TimeUTC":"2025-12-12 14:19:01","timestampInMs":1765549141435,"requestPath":"api.gaiyatime.com/api/quota-status","requestMethod":"GET","requestQueryString":"user_id=f76fae0e-1e5b-40f1-9c8d-0d138aa65639&user_tier=pro","responseStatusCode":"","requestId":"4m8fd-1765549139692-d0ec2520f98a","requestUserAgent":"python-requests/2.32.4","environment":"production","branch":"main","vercelCache":"","host":"api.gaiyatime.com","deploymentDomain":"api.gaiyatime.com","deploymentId":"dpl_2aMNxyLN1UYnCCzhMVrg1pooffv1","traceId":"","sessionId":"","type":"serverless","function":"","level":"info","message":"HTTP Request: GET https://qpgypaxwjgcirssydgqh.supabase.co/rest/v1/user_quotas?select=%2A&user_id=eq.f76fae0e-1e5b-40f1-9c8d-0d138aa65639 \"HTTP/2 200 OK\"","durationMs":"","region":"","maxMemoryUsed":"","memorySize":"","invocationId":"","instanceId":"","concurrency":""},{"projectId":"prj_TEhZ3iXh2MfgelKntnyiJGpEFO9P","TimeUTC":"2025-12-12 14:19:01","timestampInMs":1765549141437,"requestPath":"api.gaiyatime.com/api/quota-status","requestMethod":"GET","requestQueryString":"user_id=f76fae0e-1e5b-40f1-9c8d-0d138aa65639&user_tier=pro","responseStatusCode":"","requestId":"4m8fd-1765549139692-d0ec2520f98a","requestUserAgent":"python-requests/2.32.4","environment":"production","branch":"main","vercelCache":"","host":"api.gaiyatime.com","deploymentDomain":"api.gaiyatime.com","deploymentId":"dpl_2aMNxyLN1UYnCCzhMVrg1pooffv1","traceId":"","sessionId":"","type":"serverless","function":"","level":"error","message":"User tier changed: free -> pro, updating...","durationMs":"","region":"","maxMemoryUsed":"","memorySize":"","invocationId":"","instanceId":"","concurrency":""},{"projectId":"prj_TEhZ3iXh2MfgelKntnyiJGpEFO9P","TimeUTC":"2025-12-12 14:19:02","timestampInMs":1765549142239,"requestPath":"api.gaiyatime.com/api/quota-status","requestMethod":"GET","requestQueryString":"user_id=f76fae0e-1e5b-40f1-9c8d-0d138aa65639&user_tier=pro","responseStatusCode":"","requestId":"4m8fd-1765549139692-d0ec2520f98a","requestUserAgent":"python-requests/2.32.4","environment":"production","branch":"main","vercelCache":"","host":"api.gaiyatime.com","deploymentDomain":"api.gaiyatime.com","deploymentId":"dpl_2aMNxyLN1UYnCCzhMVrg1pooffv1","traceId":"","sessionId":"","type":"serverless","function":"","level":"info","message":"HTTP Request: PATCH https://qpgypaxwjgcirssydgqh.supabase.co/rest/v1/user_quotas?user_id=eq.f76fae0e-1e5b-40f1-9c8d-0d138aa65639 \"HTTP/2 200 OK\"","durationMs":"","region":"","maxMemoryUsed":"","memorySize":"","invocationId":"","instanceId":"","concurrency":""},{"projectId":"prj_TEhZ3iXh2MfgelKntnyiJGpEFO9P","TimeUTC":"2025-12-12 14:19:02","timestampInMs":1765549142239,"requestPath":"api.gaiyatime.com/api/quota-status","requestMethod":"GET","requestQueryString":"user_id=f76fae0e-1e5b-40f1-9c8d-0d138aa65639&user_tier=pro","responseStatusCode":"","requestId":"4m8fd-1765549139692-d0ec2520f98a","requestUserAgent":"python-requests/2.32.4","environment":"production","branch":"main","vercelCache":"","host":"api.gaiyatime.com","deploymentDomain":"api.gaiyatime.com","deploymentId":"dpl_2aMNxyLN1UYnCCzhMVrg1pooffv1","traceId":"","sessionId":"","type":"serverless","function":"","level":"error","message":"Updated user tier from free to pro","durationMs":"","region":"","maxMemoryUsed":"","memorySize":"","invocationId":"","instanceId":"","concurrency":""},{"projectId":"prj_TEhZ3iXh2MfgelKntnyiJGpEFO9P","TimeUTC":"2025-12-12 14:19:02","timestampInMs":1765549142518,"requestPath":"api.gaiyatime.com/api/quota-status","requestMethod":"GET","requestQueryString":"user_id=f76fae0e-1e5b-40f1-9c8d-0d138aa65639&user_tier=pro","responseStatusCode":"","requestId":"4m8fd-1765549139692-d0ec2520f98a","requestUserAgent":"python-requests/2.32.4","environment":"production","branch":"main","vercelCache":"","host":"api.gaiyatime.com","deploymentDomain":"api.gaiyatime.com","deploymentId":"dpl_2aMNxyLN1UYnCCzhMVrg1pooffv1","traceId":"","sessionId":"","type":"serverless","function":"","level":"info","message":"HTTP Request: GET https://qpgypaxwjgcirssydgqh.supabase.co/rest/v1/user_quotas?select=%2A&user_id=eq.f76fae0e-1e5b-40f1-9c8d-0d138aa65639 \"HTTP/2 200 OK\"","durationMs":"","region":"","maxMemoryUsed":"","memorySize":"","invocationId":"","instanceId":"","concurrency":""},{"projectId":"prj_TEhZ3iXh2MfgelKntnyiJGpEFO9P","TimeUTC":"2025-12-12 14:19:02","timestampInMs":1765549142519,"requestPath":"api.gaiyatime.com/api/quota-status","requestMethod":"GET","requestQueryString":"user_id=f76fae0e-1e5b-40f1-9c8d-0d138aa65639&user_tier=pro","responseStatusCode":"","requestId":"4m8fd-1765549139692-d0ec2520f98a","requestUserAgent":"python-requests/2.32.4","environment":"production","branch":"main","vercelCache":"","host":"api.gaiyatime.com","deploymentDomain":"api.gaiyatime.com","deploymentId":"dpl_2aMNxyLN1UYnCCzhMVrg1pooffv1","traceId":"","sessionId":"","type":"serverless","function":"","level":"error","message":"Returning quota: {'remaining': {'daily_plan': 17, 'weekly_report': 10, 'chat': 100}, 'user_tier': 'pro'}","durationMs":"","region":"","maxMemoryUsed":"","memorySize":"","invocationId":"","instanceId":"","concurrency":""},{"projectId":"prj_TEhZ3iXh2MfgelKntnyiJGpEFO9P","TimeUTC":"2025-12-12 14:19:02","timestampInMs":1765549142519,"requestPath":"api.gaiyatime.com/api/quota-status","requestMethod":"GET","requestQueryString":"user_id=f76fae0e-1e5b-40f1-9c8d-0d138aa65639&user_tier=pro","responseStatusCode":"","requestId":"4m8fd-1765549139692-d0ec2520f98a","requestUserAgent":"python-requests/2.32.4","environment":"production","branch":"main","vercelCache":"","host":"api.gaiyatime.com","deploymentDomain":"api.gaiyatime.com","deploymentId":"dpl_2aMNxyLN1UYnCCzhMVrg1pooffv1","traceId":"","sessionId":"","type":"serverless","function":"","level":"info","message":"127.0.0.1 - - [12/Dec/2025 14:19:02] \"GET /api/quota-status?user_id=f76fae0e-1e5b-40f1-9c8d-0d138aa65639&user_tier=pro HTTP/1.1\" 200 -","durationMs":"","region":"","maxMemoryUsed":"","memorySize":"","invocationId":"","instanceId":"","concurrency":""},{"projectId":"prj_TEhZ3iXh2MfgelKntnyiJGpEFO9P","TimeUTC":"2025-12-12 14:18:59","timestampInMs":1765549139692,"requestPath":"api.gaiyatime.com/api/quota-status","requestMethod":"GET","requestQueryString":"user_id=f76fae0e-1e5b-40f1-9c8d-0d138aa65639&user_tier=pro","responseStatusCode":"","requestId":"4m8fd-1765549139692-d0ec2520f98a","requestUserAgent":"python-requests/2.32.4","environment":"production","branch":"main","vercelCache":"","host":"api.gaiyatime.com","deploymentDomain":"api.gaiyatime.com","deploymentId":"dpl_2aMNxyLN1UYnCCzhMVrg1pooffv1","traceId":"","sessionId":"","type":"serverless","function":"/api/quota-status","level":"","message":"","durationMs":2446,"region":"iad1","maxMemoryUsed":277,"memorySize":2048,"invocationId":"01KC9EVT2K69WBD6SKZ87AG39K","instanceId":"SolRvrylshif","concurrency":2}]